Workbook

Sheet Instruções gerais
A3: A planilha foi criada para facilitar o acompanhamento das posições de ativos e fundos da sua carteira de investimentos. Ela está estruturada em várias abas, com o objetivo de fornecer uma visão clara e consolidada sobre a performance e a composição da sua carteira. Estrutura da Planilha: Dashboard: Esta aba apresenta gráficos e informações visuais sobre a composição geral da sua carteira de investimentos. Aqui, você pode visualizar rapidamente como está distribuído o seu portfólio entre diferentes classes de ativos, como ações, renda fixa e fundos imobiliários. Geral: Na aba "Geral", você encontrará uma tabela consolidada com a visão completa das classes de ativos da sua carteira. Essa aba oferece um panorama global dos seus investimentos, ajudando a entender como seus recursos estão distribuídos entre diferentes categorias. Abas das Classes de Ativos: As demais abas são dedicadas a classes de ativos específicas (como ações, fundos imobiliários, renda fixa, etc.). Nessas abas, você deve preencher as posições atuais de cada ativo ou fundo que compõe sua carteira. Ao atualizar essas informações, os cálculos e gráficos das outras abas serão automaticamente ajustados, garantindo que a planilha reflita com precisão sua situação atual. Importante: Sobre a fórmula HISTÓRICO DE AÇÕES A planilha utiliza a fórmula HISTÓRICO DE AÇÕES para atualizar automaticamente os preços dos ativos. No entanto, essa funcionalidade está disponível apenas nas versões do Excel 365, desde que o usuário tenha uma assinatura ativa (Microsoft 365 Personal, Microsoft 365 Family, Microsoft 365 Business Standard ou Microsoft 365 Business Premium) e esteja conectado à internet. Se você estiver utilizando uma versão anterior, essa fórmula não estará disponível. Nesse caso, os preços e outros dados devem ser inseridos manualmente para que a planilha funcione corretamente. Para mais informações, acesse: https://support.microsoft.com/pt-br/office/fun%C3%A7%C3%A3o-hist%C3%B3ricodea%C3%A7%C3%B5es-1ac8b5b3-5f62-4d94-8ab8-7504ec7239a8

Sheet Dashboard

Sheet Geral
B3: Visão Geral de Investimentos
B6: Total Investido | C6: =SUM(C11:C97) -> 1778050 | D6: ="Δ "&TEXT(C7-C6,"#.#") -> Δ -154.063 | E6: =C7/C6-1 -> -0.08664717
B7: Total Atual | C7: =SUM(D11:D97) -> 1623987
B10: Ativo | C10: Investido | D10: Atual | E10: % Carteira | F10: Balanceamento Meta | G10: Ajustar | H10: Ajuste Real
B11: Dívida Corporativa | C11: ='Dívida Corporativa'!C6 -> 347000 | D11: ='Dívida Corporativa'!C7 -> 301520 | E11: =D11/$C$7 -> 0.18566651 | F11: 0.15 | G11: =F11-E11 -> -0.035666511 | H11: =$C$7*G11 -> -57921.95
B12: FIIs | C12: =FIIs!C5 -> 859050 | D12: =FIIs!C6 -> 733082 | E12: =D12/$C$7 -> 0.45140879 | F12: 0.4 | G12: =F12-E12 -> -0.051408786 | H12: =$C$7*G12 -> -83487.2
B13: Títulos Públicos | C13: ='Títulos Públicos'!C6 -> 230000 | D13: ='Títulos Públicos'!C7 -> 222400 | E13: =D13/$C$7 -> 0.13694691 | F13: 0.15 | G13: =F13-E13 -> 0.013053091 | H13: =$C$7*G13 -> 21198.05
B14: Ações | C14: =Ações!C6 -> 342000 | D14: =Ações!C7 -> 366985 | E14: =D14/$C$7 -> 0.22597779 | F14: 0.3 | G14: =F14-E14 -> 0.074022206 | H14: =$C$7*G14 -> 120211.1

Sheet Dívida Corporativa
B6: Total Investido | C6: =SUM(H11:H95) -> 347000 | D6: ="Δ "&TEXT(C7-C6,"#.#") -> Δ -45.480 | E6: =C7/C6-1 -> -0.13106628
B7: Total Atual | C7: =SUM(I11:I95) -> 301520
B10: Ativo | C10: Data | D10: Corretora | E10: Preço Médio | F10: Quantidade | G10: Preço Atual | H10: Investido | I10: Atual | J10: L/P | K10: % L/P | L10: % Carteira Dívida Corporativa
B11: JURO11 | C11: 45383 | D11: BTG | E11: 100 | F11: 1000 | G11: =IFERROR(_xlfn.STOCKHISTORY(B11,TODAY(),,0,0,1),IFERROR(_xlfn.STOCKHISTORY(B11,TODAY()-1,,0,0,1),IFERROR(_xlfn.STOCKHISTORY(B11,TODAY()-2,,0,0,1),_xlfn.STOCKHISTORY(B11,TODAY()-3,,0,0,1)))) -> 92.12 | H11: =E11*F11 -> 100000 | I11: =F11*G11 -> 92120 | J11: =I11-H11 -> -7880 | K11: =I11/H11-1 -> -0.0788 | L11: =I11/$C$7 -> 0.30551871
B12: KDIF11 | C12: 45383 | D12: BTG | E12: 140 | F12: 1000 | G12: =IFERROR(_xlfn.STOCKHISTORY(B12,TODAY(),,0,0,1),IFERROR(_xlfn.STOCKHISTORY(B12,TODAY()-1,,0,0,1),IFERROR(_xlfn.STOCKHISTORY(B12,TODAY()-2,,0,0,1),_xlfn.STOCKHISTORY(B12,TODAY()-3,,0,0,1)))) -> 120.5 | H12: =E12*F12 -> 140000 | I12: =F12*G12 -> 120500 | J12: =I12-H12 -> -19500 | K12: =I12/H12-1 -> -0.13928571 | L12: =I12/$C$7 -> 0.39964181
B13: IFRA11 | C13: 45383 | D13: BTG | E13: 107 | F13: 1000 | G13: =IFERROR(_xlfn.STOCKHISTORY(B13,TODAY(),,0,0,1),IFERROR(_xlfn.STOCKHISTORY(B13,TODAY()-1,,0,0,1),IFERROR(_xlfn.STOCKHISTORY(B13,TODAY()-2,,0,0,1),_xlfn.STOCKHISTORY(B13,TODAY()-3,,0,0,1)))) -> 88.9 | H13: =E13*F13 -> 107000 | I13: =F13*G13 -> 88900 | J13: =I13-H13 -> -18100 | K13: =I13/H13-1 -> -0.16915888 | L13: =I13/$C$7 -> 0.29483948

Sheet FIIs
B5: Total Investido | C5: =SUM(H10:H87) -> 859050 | E5: ="Δ "&TEXT(C6-C5,"#.#") -> Δ -125.968 | F5: =C6/C5-1 -> -0.1466364
B6: Total Atual | C6: =SUM(I10:I87) -> 733082
B9: Ativo | C9: Data | D9: Corretora | E9: Preço Médio | F9: Quantidade | G9: Preço Atual | H9: Investido | I9: Atual | J9: L/P | K9: % L/P | L9: % Carteira FII
B10: VISC11 | C10: 44958 | D10: BTG | E10: 100 | F10: 1000 | G10: {=IFERROR(_xlfn.STOCKHISTORY(B10,TODAY(),,0,0,1),IFERROR(_xlfn.STOCKHISTORY(B10,TODAY()-1,,0,0,1),IFERROR(_xlfn.STOCKHISTORY(B10,TODAY()-2,,0,0,1),_xlfn.STOCKHISTORY(B10,TODAY()-3,,0,0,1))))} -> 92 | H10: =E10*F10 -> 100000 | I10: =F10*G10 -> 92000 | J10: =I10-H10 -> -8000 | K10: =I10/H10-1 -> -0.08 | L10: =I10/$C$6 -> 0.12549756
B11: PORD11 | C11: 45108 | D11: BTG | E11: 9 | F11: 300 | G11: {=IFERROR(_xlfn.STOCKHISTORY(B11,TODAY(),,0,0,1),IFERROR(_xlfn.STOCKHISTORY(B11,TODAY()-1,,0,0,1),IFERROR(_xlfn.STOCKHISTORY(B11,TODAY()-2,,0,0,1),_xlfn.STOCKHISTORY(B11,TODAY()-3,,0,0,1))))} -> 7.35 | H11: =E11*F11 -> 2700 | I11: =F11*G11 -> 2205 | J11: =I11-H11 -> -495 | K11: =I11/H11-1 -> -0.18333333 | L11: =I11/$C$6 -> 0.0030078491
B12: XPML11 | C12: 45108 | D12: BTG | E12: 108 | F12: 2000 | G12: {=IFERROR(_xlfn.STOCKHISTORY(B12,TODAY(),,0,0,1),IFERROR(_xlfn.STOCKHISTORY(B12,TODAY()-1,,0,0,1),IFERROR(_xlfn.STOCKHISTORY(B12,TODAY()-2,,0,0,1),_xlfn.STOCKHISTORY(B12,TODAY()-3,,0,0,1))))} -> 97.65 | H12: =E12*F12 -> 216000 | I12: =F12*G12 -> 195300 | J12: =I12-H12 -> -20700 | K12: =I12/H12-1 -> -0.095833333 | L12: =I12/$C$6 -> 0.26640949
B13: RVBI11 | C13: 45294 | D13: BTG | E13: 58 | F13: 1000 | G13: {=IFERROR(_xlfn.STOCKHISTORY(B13,TODAY(),,0,0,1),IFERROR(_xlfn.STOCKHISTORY(B13,TODAY()-1,,0,0,1),IFERROR(_xlfn.STOCKHISTORY(B13,TODAY()-2,,0,0,1),_xlfn.STOCKHISTORY(B13,TODAY()-3,,0,0,1))))} -> 61.48 | H13: =E13*F13 -> 58000 | I13: =F13*G13 -> 61480 | J13: =I13-H13 -> 3480 | K13: =I13/H13-1 -> 0.06 | L13: =I13/$C$6 -> 0.083865106
B14: BTCI11 | C14: 45174 | D14: BTG | E14: 9.5 | F14: 1500 | G14: {=IFERROR(_xlfn.STOCKHISTORY(B14,TODAY(),,0,0,1),IFERROR(_xlfn.STOCKHISTORY(B14,TODAY()-1,,0,0,1),IFERROR(_xlfn.STOCKHISTORY(B14,TODAY()-2,,0,0,1),_xlfn.STOCKHISTORY(B14,TODAY()-3,,0,0,1))))} -> 8 | H14: =E14*F14 -> 14250 | I14: =F14*G14 -> 12000 | J14: =I14-H14 -> -2250 | K14: =I14/H14-1 -> -0.15789474 | L14: =I14/$C$6 -> 0.016369247
B15: RBFF11 | C15: 44598 | D15: BTG | E15: 50 | F15: 600 | G15: {=IFERROR(_xlfn.STOCKHISTORY(B15,TODAY(),,0,0,1),IFERROR(_xlfn.STOCKHISTORY(B15,TODAY()-1,,0,0,1),IFERROR(_xlfn.STOCKHISTORY(B15,TODAY()-2,,0,0,1),_xlfn.STOCKHISTORY(B15,TODAY()-3,,0,0,1))))} -> 46.92 | H15: =E15*F15 -> 30000 | I15: =F15*G15 -> 28152 | J15: =I15-H15 -> -1848 | K15: =I15/H15-1 -> -0.0616 | L15: =I15/$C$6 -> 0.038402252
B16: PVBI11 | C16: 44866 | D16: BTG | E16: 90 | F16: 500 | G16: {=IFERROR(_xlfn.STOCKHISTORY(B16,TODAY(),,0,0,1),IFERROR(_xlfn.STOCKHISTORY(B16,TODAY()-1,,0,0,1),IFERROR(_xlfn.STOCKHISTORY(B16,TODAY()-2,,0,0,1),_xlfn.STOCKHISTORY(B16,TODAY()-3,,0,0,1))))} -> 74.04 | H16: =E16*F16 -> 45000 | I16: =F16*G16 -> 37020 | J16: =I16-H16 -> -7980 | K16: =I16/H16-1 -> -0.17733333 | L16: =I16/$C$6 -> 0.050499126
B17: GARE11 | C17: 45174 | D17: BTG | E17: 9 | F17: 500 | G17: 8.2 | H17: =E17*F17 -> 4500 | I17: =F17*G17 -> 4100 | J17: =I17-H17 -> -400 | K17: =I17/H17-1 -> -0.088888889 | L17: =I17/$C$6 -> 0.0055928259
B18: KFOF11 | C18: 44598 | D18: BTG | E18: 93 | F18: 2000 | G18: {=IFERROR(_xlfn.STOCKHISTORY(B18,TODAY(),,0,0,1),IFERROR(_xlfn.STOCKHISTORY(B18,TODAY()-1,,0,0,1),IFERROR(_xlfn.STOCKHISTORY(B18,TODAY()-2,,0,0,1),_xlfn.STOCKHISTORY(B18,TODAY()-3,,0,0,1))))} -> 70.84 | H18: =E18*F18 -> 186000 | I18: =F18*G18 -> 141680 | J18: =I18-H18 -> -44320 | K18: =I18/H18-1 -> -0.23827957 | L18: =I18/$C$6 -> 0.19326624
B19: BRCR11 | C19: 44866 | D19: BTG | E19: 68 | F19: 400 | G19: {=IFERROR(_xlfn.STOCKHISTORY(B19,TODAY(),,0,0,1),IFERROR(_xlfn.STOCKHISTORY(B19,TODAY()-1,,0,0,1),IFERROR(_xlfn.STOCKHISTORY(B19,TODAY()-2,,0,0,1),_xlfn.STOCKHISTORY(B19,TODAY()-3,,0,0,1))))} -> 40.14 | H19: =E19*F19 -> 27200 | I19: =F19*G19 -> 16056 | J19: =I19-H19 -> -11144 | K19: =I19/H19-1 -> -0.40970588 | L19: =I19/$C$6 -> 0.021902052
B20: VILG11 | C20: 44598 | D20: BTG | E20: 80 | F20: 300 | G20: {=IFERROR(_xlfn.STOCKHISTORY(B20,TODAY(),,0,0,1),IFERROR(_xlfn.STOCKHISTORY(B20,TODAY()-1,,0,0,1),IFERROR(_xlfn.STOCKHISTORY(B20,TODAY()-2,,0,0,1),_xlfn.STOCKHISTORY(B20,TODAY()-3,,0,0,1))))} -> 72.02 | H20: =E20*F20 -> 24000 | I20: =F20*G20 -> 21606 | J20: =I20-H20 -> -2394 | K20: =I20/H20-1 -> -0.09975 | L20: =I20/$C$6 -> 0.029472828
B21: CPTS11 | C21: 44866 | D21: BTG | E21: 8 | F21: 500 | G21: {=IFERROR(_xlfn.STOCKHISTORY(B21,TODAY(),,0,0,1),IFERROR(_xlfn.STOCKHISTORY(B21,TODAY()-1,,0,0,1),IFERROR(_xlfn.STOCKHISTORY(B21,TODAY()-2,,0,0,1),_xlfn.STOCKHISTORY(B21,TODAY()-3,,0,0,1))))} -> 6.46 | H21: =E21*F21 -> 4000 | I21: =F21*G21 -> 3230 | J21: =I21-H21 -> -770 | K21: =I21/H21-1 -> -0.1925 | L21: =I21/$C$6 -> 0.0044060555
B22: KNSC11 | C22: 44598 | D22: BTG | E22: 9.2 | F22: 2000 | G22: {=IFERROR(_xlfn.STOCKHISTORY(B22,TODAY(),,0,0,1),IFERROR(_xlfn.STOCKHISTORY(B22,TODAY()-1,,0,0,1),IFERROR(_xlfn.STOCKHISTORY(B22,TODAY()-2,,0,0,1),_xlfn.STOCKHISTORY(B22,TODAY()-3,,0,0,1))))} -> 8.03 | H22: =E22*F22 -> 18400 | I22: =F22*G22 -> 16060 | J22: =I22-H22 -> -2340 | K22: =I22/H22-1 -> -0.12717391 | L22: =I22/$C$6 -> 0.021907508
B23: LVBI11 | C23: 44866 | D23: BTG | E23: 115 | F23: 300 | G23: {=IFERROR(_xlfn.STOCKHISTORY(B23,TODAY(),,0,0,1),IFERROR(_xlfn.STOCKHISTORY(B23,TODAY()-1,,0,0,1),IFERROR(_xlfn.STOCKHISTORY(B23,TODAY()-2,,0,0,1),_xlfn.STOCKHISTORY(B23,TODAY()-3,,0,0,1))))} -> 91.44 | H23: =E23*F23 -> 34500 | I23: =F23*G23 -> 27432 | J23: =I23-H23 -> -7068 | K23: =I23/H23-1 -> -0.20486957 | L23: =I23/$C$6 -> 0.037420098
B24: JSRE11 | C24: 45174 | D24: BTG | E24: 70 | F24: 500 | G24: {=IFERROR(_xlfn.STOCKHISTORY(B24,TODAY(),,0,0,1),IFERROR(_xlfn.STOCKHISTORY(B24,TODAY()-1,,0,0,1),IFERROR(_xlfn.STOCKHISTORY(B24,TODAY()-2,,0,0,1),_xlfn.STOCKHISTORY(B24,TODAY()-3,,0,0,1))))} -> 57.72 | H24: =E24*F24 -> 35000 | I24: =F24*G24 -> 28860 | J24: =I24-H24 -> -6140 | K24: =I24/H24-1 -> -0.17542857 | L24: =I24/$C$6 -> 0.039368038
B25: RBVA11 | C25: 44598 | D25: BTG | E25: 100 | F25: 400 | G25: {=IFERROR(_xlfn.STOCKHISTORY(B25,TODAY(),,0,0,1),IFERROR(_xlfn.STOCKHISTORY(B25,TODAY()-1,,0,0,1),IFERROR(_xlfn.STOCKHISTORY(B25,TODAY()-2,,0,0,1),_xlfn.STOCKHISTORY(B25,TODAY()-3,,0,0,1))))} -> 82 | H25: =E25*F25 -> 40000 | I25: =F25*G25 -> 32800 | J25: =I25-H25 -> -7200 | K25: =I25/H25-1 -> -0.18 | L25: =I25/$C$6 -> 0.044742607
B26: PATL11 | C26: 44866 | D26: BTG | E26: 65 | F26: 300 | G26: {=IFERROR(_xlfn.STOCKHISTORY(B26,TODAY(),,0,0,1),IFERROR(_xlfn.STOCKHISTORY(B26,TODAY()-1,,0,0,1),IFERROR(_xlfn.STOCKHISTORY(B26,TODAY()-2,,0,0,1),_xlfn.STOCKHISTORY(B26,TODAY()-3,,0,0,1))))} -> 43.67 | H26: =E26*F26 -> 19500 | I26: =F26*G26 -> 13101 | J26: =I26-H26 -> -6399 | K26: =I26/H26-1 -> -0.32815385 | L26: =I26/$C$6 -> 0.017871125

Sheet Títulos Públicos
B6: Total Investido | C6: =SUM(G11:G101) -> 230000 | D6: ="Δ "&TEXT(C7-C6,"#.#") -> Δ -7.600 | E6: =C7/C6-1 -> -0.033043478
B7: Total Atual | C7: =SUM(H11:H101) -> 222400
B10: Data | C10: Tipo | D10: Nome | E10: Data Vencimento | F10: Corretora | G10: Investido | H10: Atual | I10: L/P | J10: % L/P
B11: 45566 | C11: Indexado à Inflação | D11: Tesouro IPCA+ 2035 com Juros Semestrais | E11: 49444 | F11: XP | G11: 50000 | H11: 55600 | I11: =H11-G11 -> 5600 | J11: =H11/G11-1 -> 0.112
B12: 44713 | C12: Indexado à Inflação | D12: Tesouro IPCA+ 2040 com Juros Semestrais | E12: 51363 | F12: XP | G12: 65000 | H12: 55600 | I12: =H12-G12 -> -9400 | J12: =H12/G12-1 -> -0.14461538
B13: 45566 | C13: Indexado à Inflação | D13: Tesouro IPCA+ 2055 com Juros Semestrais | E13: 56749 | F13: XP | G13: 50000 | H13: 55600 | I13: =H13-G13 -> 5600 | J13: =H13/G13-1 -> 0.112
B14: 44713 | C14: Pré-fixado | D14: Tesouro Prefixado com Juros Semestrais | E14: 49310 | F14: XP | G14: 65000 | H14: 55600 | I14: =H14-G14 -> -9400 | J14: =H14/G14-1 -> -0.14461538

Sheet Ações
B6: Total Investido | C6: =SUM(H11:H98) -> 342000 | E6: ="Δ "&TEXT(C7-C6,"#.#") -> Δ 24.985 | F6: =C7/C6-1 -> 0.073055556
B7: Total Atual | C7: =SUM(I11:I98) -> 366985
B10: Ativo | C10: Data | D10: Corretora | E10: Preço Médio | F10: Quantidade | G10: Preço Atual | H10: Investido | I10: Atual | J10: L/P | K10: % L/P | L10: % Carteira Ações
B11: BBAS3 | C11: 45383 | D11: BTG | E11: 20 | F11: 1000 | G11: =IFERROR(_xlfn.STOCKHISTORY(B11,TODAY(),,0,0,1),IFERROR(_xlfn.STOCKHISTORY(B11,TODAY()-1,,0,0,1),IFERROR(_xlfn.STOCKHISTORY(B11,TODAY()-2,,0,0,1),_xlfn.STOCKHISTORY(B11,TODAY()-3,,0,0,1)))) -> 24.51 | H11: =E11*F11 -> 20000 | I11: =F11*G11 -> 24510 | J11: =I11-H11 -> 4510 | K11: =I11/H11-1 -> 0.2255 | L11: =I11/$C$7 -> 0.066787471
B12: TGMA3 | C12: 44228 | D12: BTG | E12: 20 | F12: 1500 | G12: =IFERROR(_xlfn.STOCKHISTORY(B12,TODAY(),,0,0,1),IFERROR(_xlfn.STOCKHISTORY(B12,TODAY()-1,,0,0,1),IFERROR(_xlfn.STOCKHISTORY(B12,TODAY()-2,,0,0,1),_xlfn.STOCKHISTORY(B12,TODAY()-3,,0,0,1)))) -> 31.11 | H12: =E12*F12 -> 30000 | I12: =F12*G12 -> 46665 | J12: =I12-H12 -> 16665 | K12: =I12/H12-1 -> 0.5555 | L12: =I12/$C$7 -> 0.12715779
B13: KLBN11 | C13: 45050 | D13: BTG | E13: 22 | F13: 2000 | G13: {=IFERROR(_xlfn.STOCKHISTORY(B13,TODAY(),,0,0,1),IFERROR(_xlfn.STOCKHISTORY(B13,TODAY()-1,,0,0,1),IFERROR(_xlfn.STOCKHISTORY(B13,TODAY()-2,,0,0,1),_xlfn.STOCKHISTORY(B13,TODAY()-3,,0,0,1))))} -> 23.08 | H13: =E13*F13 -> 44000 | I13: =F13*G13 -> 46160 | J13: =I13-H13 -> 2160 | K13: =I13/H13-1 -> 0.049090909 | L13: =I13/$C$7 -> 0.12578171
B14: SLCE3 | C14: 45383 | D14: BTG | E14: 18 | F14: 6000 | G14: {=IFERROR(_xlfn.STOCKHISTORY(B14,TODAY(),,0,0,1),IFERROR(_xlfn.STOCKHISTORY(B14,TODAY()-1,,0,0,1),IFERROR(_xlfn.STOCKHISTORY(B14,TODAY()-2,,0,0,1),_xlfn.STOCKHISTORY(B14,TODAY()-3,,0,0,1))))} -> 19.17 | H14: =E14*F14 -> 108000 | I14: =F14*G14 -> 115020 | J14: =I14-H14 -> 7020 | K14: =I14/H14-1 -> 0.065 | L14: =I14/$C$7 -> 0.3134188
B15: KEPL3 | C15: 44228 | D15: BTG | E15: 10 | F15: 2000 | G15: {=IFERROR(_xlfn.STOCKHISTORY(B15,TODAY(),,0,0,1),IFERROR(_xlfn.STOCKHISTORY(B15,TODAY()-1,,0,0,1),IFERROR(_xlfn.STOCKHISTORY(B15,TODAY()-2,,0,0,1),_xlfn.STOCKHISTORY(B15,TODAY()-3,,0,0,1))))} -> 9.55 | H15: =E15*F15 -> 20000 | I15: =F15*G15 -> 19100 | J15: =I15-H15 -> -900 | K15: =I15/H15-1 -> -0.045 | L15: =I15/$C$7 -> 0.052045724
B16: BBDC4 | C16: 44228 | D16: BTG | E16: 15 | F16: 2500 | G16: {=IFERROR(_xlfn.STOCKHISTORY(B16,TODAY(),,0,0,1),IFERROR(_xlfn.STOCKHISTORY(B16,TODAY()-1,,0,0,1),IFERROR(_xlfn.STOCKHISTORY(B16,TODAY()-2,,0,0,1),_xlfn.STOCKHISTORY(B16,TODAY()-3,,0,0,1))))} -> 12.1 | H16: =E16*F16 -> 37500 | I16: =F16*G16 -> 30250 | J16: =I16-H16 -> -7250 | K16: =I16/H16-1 -> -0.19333333 | L16: =I16/$C$7 -> 0.082428437
B17: ABCB4 | C17: 45050 | D17: BTG | E17: 20 | F17: 1000 | G17: {=IFERROR(_xlfn.STOCKHISTORY(B17,TODAY(),,0,0,1),IFERROR(_xlfn.STOCKHISTORY(B17,TODAY()-1,,0,0,1),IFERROR(_xlfn.STOCKHISTORY(B17,TODAY()-2,,0,0,1),_xlfn.STOCKHISTORY(B17,TODAY()-3,,0,0,1))))} -> 20.7 | H17: =E17*F17 -> 20000 | I17: =F17*G17 -> 20700 | J17: =I17-H17 -> 700 | K17: =I17/H17-1 -> 0.035 | L17: =I17/$C$7 -> 0.056405575
B18: SAPR11 | C18: 44228 | D18: BTG | E18: 28 | F18: 1000 | G18: {=IFERROR(_xlfn.STOCKHISTORY(B18,TODAY(),,0,0,1),IFERROR(_xlfn.STOCKHISTORY(B18,TODAY()-1,,0,0,1),IFERROR(_xlfn.STOCKHISTORY(B18,TODAY()-2,,0,0,1),_xlfn.STOCKHISTORY(B18,TODAY()-3,,0,0,1))))} -> 28.35 | H18: =E18*F18 -> 28000 | I18: =F18*G18 -> 28350 | J18: =I18-H18 -> 350 | K18: =I18/H18-1 -> 0.0125 | L18: =I18/$C$7 -> 0.077251114
B19: TASA4 | C19: 45050 | D19: BTG | E19: 13.5 | F19: 1000 | G19: {=IFERROR(_xlfn.STOCKHISTORY(B19,TODAY(),,0,0,1),IFERROR(_xlfn.STOCKHISTORY(B19,TODAY()-1,,0,0,1),IFERROR(_xlfn.STOCKHISTORY(B19,TODAY()-2,,0,0,1),_xlfn.STOCKHISTORY(B19,TODAY()-3,,0,0,1))))} -> 9 | H19: =E19*F19 -> 13500 | I19: =F19*G19 -> 9000 | J19: =I19-H19 -> -4500 | K19: =I19/H19-1 -> -0.33333333 | L19: =I19/$C$7 -> 0.024524163
B20: BMGB4 | C20: 45051 | D20: BTG | E20: 3 | F20: 7000 | G20: {=IFERROR(_xlfn.STOCKHISTORY(B20,TODAY(),,0,0,1),IFERROR(_xlfn.STOCKHISTORY(B20,TODAY()-1,,0,0,1),IFERROR(_xlfn.STOCKHISTORY(B20,TODAY()-2,,0,0,1),_xlfn.STOCKHISTORY(B20,TODAY()-3,,0,0,1))))} -> 3.89 | H20: =E20*F20 -> 21000 | I20: =F20*G20 -> 27230 | J20: =I20-H20 -> 6230 | K20: =I20/H20-1 -> 0.29666667 | L20: =I20/$C$7 -> 0.074199218
