Workbook

Sheet Instruções gerais
A1: b
A3: A planilha foi criada para facilitar o acompanhamento das posições de ativos e fundos da sua carteira de investimentos. Ela está estruturada em várias abas, com o objetivo de fornecer uma visão clara e consolidada sobre a performance e a composição da sua carteira. Estrutura da Planilha: Dashboard: Esta aba apresenta gráficos e informações visuais sobre a composição geral da sua carteira de investimentos. Aqui, você pode visualizar rapidamente como está distribuído o seu portfólio entre diferentes classes de ativos, como ações, renda fixa e fundos imobiliários. Geral: Na aba "Geral", você encontrará uma tabela consolidada com a visão completa das classes de ativos da sua carteira. Essa aba oferece um panorama global dos seus investimentos, ajudando a entender como seus recursos estão distribuídos entre diferentes categorias. Abas das Classes de Ativos: As demais abas são dedicadas a classes de ativos específicas (como ações, fundos imobiliários, renda fixa, etc.). Nessas abas, você deve preencher as posições atuais de cada ativo ou fundo que compõe sua carteira. Ao atualizar essas informações, os cálculos e gráficos das outras abas serão automaticamente ajustados, garantindo que a planilha reflita com precisão sua situação atual. Importante: Sobre a fórmula HISTÓRICO DE AÇÕES A planilha utiliza a fórmula HISTÓRICO DE AÇÕES para atualizar automaticamente os preços dos ativos. No entanto, essa funcionalidade está disponível apenas nas versões do Excel 365, desde que o usuário tenha uma assinatura ativa (Microsoft 365 Personal, Microsoft 365 Family, Microsoft 365 Business Standard ou Microsoft 365 Business Premium) e esteja conectado à internet. Se você estiver utilizando uma versão anterior, essa fórmula não estará disponível. Nesse caso, os preços e outros dados devem ser inseridos manualmente para que a planilha funcione corretamente. Para mais informações, acesse: https://support.microsoft.com/pt-br/office/fun%C3%A7%C3%A3o-hist%C3%B3ricodea%C3%A7%C3%B5es-1ac8b5b3-5f62-4d94-8ab8-7504ec7239a8

Sheet Dashboard

Sheet Geral
B3: Visão Geral de Investimentos
B6: Total Investido | C6: =SUM(C11:C100) -> 2436707.5 | D6: ="Δ "&TEXT(C7-C6,"#.#") -> Δ 493.023 | E6: =C7/C6-1 -> 0.20233174
B7: Total Atual | C7: =SUM(D11:D100) -> 2929730.8
B10: Ativo | C10: Investido | D10: Atual | E10: % Carteira | F10: Balanceamento Meta | G10: Ajustar | H10: Ajuste Real
B11: Renda Fixa | C11: ='Renda Fixa'!C6 -> 115000 | D11: ='Renda Fixa'!C7 -> 111200 | E11: =D11/$C$7 -> 0.037955705 | F11: 0.3 | G11: =F11-E11 -> 0.26204429 | H11: =$C$7*G11 -> 767719.25
B12: Tesouro Direto | C12: ='Tesouro Direto'!C6 -> 760000 | D12: ='Tesouro Direto'!C7 -> 831800 | E12: =D12/$C$7 -> 0.28391687 | F12: 0.3 | G12: =F12-E12 -> 0.016083133 | H12: =$C$7*G12 -> 47119.252
B13: Ações | C13: =Ações!C6 -> 627795 | D13: =Ações!C7 -> 904265 | E13: =D13/$C$7 -> 0.30865122 | F13: 0.1 | G13: =F13-E13 -> -0.20865122 | H13: =$C$7*G13 -> -611291.92
B14: Fundos | C14: =Fundos!C5 -> 635568 | D14: =Fundos!C6 -> 586418 | E14: =D14/$C$7 -> 0.20016105 | F14: 0.05 | G14: =F14-E14 -> -0.15016105 | H14: =$C$7*G14 -> -439931.46
B15: Cripto | C15: =Cripto!C7 -> 183344.55 | D15: =Cripto!C8 -> 384847.84 | E15: =D15/$C$7 -> 0.13135945 | F15: 0.1 | G15: =F15-E15 -> -0.031359453 | H15: =$C$7*G15 -> -91874.756
B16: Diversos | C16: =Diversos!C6 -> 115000 | D16: =Diversos!C7 -> 111200 | E16: =D16/$C$7 -> 0.037955705 | F16: 0.15 | G16: =F16-E16 -> 0.11204429 | H16: =$C$7*G16 -> 328259.63

Sheet Renda Fixa
B6: Total Investido | C6: =SUM(H11:H100) -> 115000 | D6: ="Δ "&TEXT(C7-C6,"#.#") -> Δ -3.800 | E6: =C7/C6-1 -> -0.033043478
B7: Total Atual | C7: =SUM(I11:I100) -> 111200
B10: Data | C10: Tipo | D10: Nome | E10: Data Vencimento | F10: Emissor | G10: Corretora | H10: Investido | I10: Atual | J10: L/P | K10: % L/P
B11: 45566 | C11: CDB Pré-fixado | D11: CDB Pré-fixado XP 101,25% do CDI | E11: 45931 | F11: XP | G11: XP | H11: 50000 | I11: 55600 | J11: =I11-H11 -> 5600 | K11: =I11/H11-1 -> 0.112
B12: 44713 | C12: CDB Pré-fixado | D12: CDB Pré-fixado XP | E12: 45931 | F12: XP | G12: XP | H12: 65000 | I12: 55600 | J12: =I12-H12 -> -9400 | K12: =I12/H12-1 -> -0.14461538

Sheet Tesouro Direto
B6: Total Investido | C6: =SUM(G11:G100) -> 760000 | D6: ="Δ "&TEXT(C7-C6,"#.#") -> Δ 71.800 | E6: =C7/C6-1 -> 0.094473684
B7: Total Atual | C7: =SUM(H11:H100) -> 831800
B10: Data | C10: Tipo | D10: Nome | E10: Data Vencimento | F10: Corretora | G10: Investido | H10: Atual | I10: L/P | J10: % L/P
B11: 44713 | C11: Tesouro Pré-fixado | D11: TESOURO PREFIXADO 2027 10,45% | E11: 46388 | F11: XP | G11: 350000 | H11: 365800 | I11: =H11-G11 -> 15800 | J11: =H11/G11-1 -> 0.045142857
B12: 44986 | C12: Tesouro Pré-fixado | D12: TESOURO PREFIXADO 2031 11,36% | E12: 49310 | F12: BTG | G12: 260000 | H12: 310000 | I12: =H12-G12 -> 50000 | J12: =H12/G12-1 -> 0.19230769
B13: 45292 | C13: Tesouro Selic | D13: TESOURO SELIC 2027 | E13: 46447 | F13: CLEAR | G13: 150000 | H13: 156000 | I13: =H13-G13 -> 6000 | J13: =H13/G13-1 -> 0.04

Sheet Ações
B6: Total Investido | C6: =SUM(H11:H102) -> 627795 | E6: ="Δ "&TEXT(C7-C6,"#.#") -> Δ 276.470 | F6: =C7/C6-1 -> 0.44038261
B7: Total Atual | C7: =SUM(I11:I102) -> 904265
B10: Ativo | C10: Data | D10: Corretora | E10: Preço Médio | F10: Quantidade | G10: Preço Atual | H10: Investido | I10: Atual | J10: L/P | K10: % L/P | L10: % Carteira Ações
B11: PETR4 | C11: 45383 | D11: BTG | E11: 14.55 | F11: 1000 | G11: =IFERROR(_xlfn.STOCKHISTORY(B11,TODAY(),,0,0,1),IFERROR(_xlfn.STOCKHISTORY(B11,TODAY()-1,,0,0,1),IFERROR(_xlfn.STOCKHISTORY(B11,TODAY()-2,,0,0,1),_xlfn.STOCKHISTORY(B11,TODAY()-3,,0,0,1)))) -> 38.1 | H11: =E11*F11 -> 14550 | I11: =F11*G11 -> 38100 | J11: =I11-H11 -> 23550 | K11: =I11/H11-1 -> 1.6185567 | L11: =I11/$C$7 -> 0.042133667
B12: BRFS3 | C12: 44228 | D12: BTG | E12: 14.55 | F12: 1500 | G12: =IFERROR(_xlfn.STOCKHISTORY(B12,TODAY(),,0,0,1),IFERROR(_xlfn.STOCKHISTORY(B12,TODAY()-1,,0,0,1),IFERROR(_xlfn.STOCKHISTORY(B12,TODAY()-2,,0,0,1),_xlfn.STOCKHISTORY(B12,TODAY()-3,,0,0,1)))) -> 27.79 | H12: =E12*F12 -> 21825 | I12: =F12*G12 -> 41685 | J12: =I12-H12 -> 19860 | K12: =I12/H12-1 -> 0.90996564 | L12: =I12/$C$7 -> 0.046098212
B13: ITUB4 | C13: 45050 | D13: BTG | E13: 27 | F13: 2000 | G13: {=IFERROR(_xlfn.STOCKHISTORY(B13,TODAY(),,0,0,1),IFERROR(_xlfn.STOCKHISTORY(B13,TODAY()-1,,0,0,1),IFERROR(_xlfn.STOCKHISTORY(B13,TODAY()-2,,0,0,1),_xlfn.STOCKHISTORY(B13,TODAY()-3,,0,0,1))))} -> 32.06 | H13: =E13*F13 -> 54000 | I13: =F13*G13 -> 64120 | J13: =I13-H13 -> 10120 | K13: =I13/H13-1 -> 0.18740741 | L13: =I13/$C$7 -> 0.070908417
B14: KLBN11 | C14: 45383 | D14: BTG | E14: 30 | F14: 6000 | G14: {=IFERROR(_xlfn.STOCKHISTORY(B14,TODAY(),,0,0,1),IFERROR(_xlfn.STOCKHISTORY(B14,TODAY()-1,,0,0,1),IFERROR(_xlfn.STOCKHISTORY(B14,TODAY()-2,,0,0,1),_xlfn.STOCKHISTORY(B14,TODAY()-3,,0,0,1))))} -> 23.08 | H14: =E14*F14 -> 180000 | I14: =F14*G14 -> 138480 | J14: =I14-H14 -> -41520 | K14: =I14/H14-1 -> -0.23066667 | L14: =I14/$C$7 -> 0.15314095
B15: VALE3 | C15: 44228 | D15: BTG | E15: 14.55 | F15: 2000 | G15: {=IFERROR(_xlfn.STOCKHISTORY(B15,TODAY(),,0,0,1),IFERROR(_xlfn.STOCKHISTORY(B15,TODAY()-1,,0,0,1),IFERROR(_xlfn.STOCKHISTORY(B15,TODAY()-2,,0,0,1),_xlfn.STOCKHISTORY(B15,TODAY()-3,,0,0,1))))} -> 55.86 | H15: =E15*F15 -> 29100 | I15: =F15*G15 -> 111720 | J15: =I15-H15 -> 82620 | K15: =I15/H15-1 -> 2.8391753 | L15: =I15/$C$7 -> 0.12354785
B16: GOGL34 | C16: 45050 | D16: BTG | E16: 14.55 | F16: 300 | G16: {=IFERROR(_xlfn.STOCKHISTORY(B16,TODAY(),,0,0,1),IFERROR(_xlfn.STOCKHISTORY(B16,TODAY()-1,,0,0,1),IFERROR(_xlfn.STOCKHISTORY(B16,TODAY()-2,,0,0,1),_xlfn.STOCKHISTORY(B16,TODAY()-3,,0,0,1))))} -> 96.5 | H16: =E16*F16 -> 4365 | I16: =F16*G16 -> 28950 | J16: =I16-H16 -> 24585 | K16: =I16/H16-1 -> 5.6323024 | L16: =I16/$C$7 -> 0.032014951
B17: ALPA4 | C17: 45383 | D17: BTG | E17: 14.55 | F17: 3000 | G17: {=IFERROR(_xlfn.STOCKHISTORY(B17,TODAY(),,0,0,1),IFERROR(_xlfn.STOCKHISTORY(B17,TODAY()-1,,0,0,1),IFERROR(_xlfn.STOCKHISTORY(B17,TODAY()-2,,0,0,1),_xlfn.STOCKHISTORY(B17,TODAY()-3,,0,0,1))))} -> 6.18 | H17: =E17*F17 -> 43650 | I17: =F17*G17 -> 18540 | J17: =I17-H17 -> -25110 | K17: =I17/H17-1 -> -0.57525773 | L17: =I17/$C$7 -> 0.020502839
B18: MGLU3 | C18: 44228 | D18: BTG | E18: 14.55 | F18: 400 | G18: {=IFERROR(_xlfn.STOCKHISTORY(B18,TODAY(),,0,0,1),IFERROR(_xlfn.STOCKHISTORY(B18,TODAY()-1,,0,0,1),IFERROR(_xlfn.STOCKHISTORY(B18,TODAY()-2,,0,0,1),_xlfn.STOCKHISTORY(B18,TODAY()-3,,0,0,1))))} -> 8.2 | H18: =E18*F18 -> 5820 | I18: =F18*G18 -> 3280 | J18: =I18-H18 -> -2540 | K18: =I18/H18-1 -> -0.43642612 | L18: =I18/$C$7 -> 0.0036272553
B19: SMTO3 | C19: 45050 | D19: BTG | E19: 14.55 | F19: 5000 | G19: {=IFERROR(_xlfn.STOCKHISTORY(B19,TODAY(),,0,0,1),IFERROR(_xlfn.STOCKHISTORY(B19,TODAY()-1,,0,0,1),IFERROR(_xlfn.STOCKHISTORY(B19,TODAY()-2,,0,0,1),_xlfn.STOCKHISTORY(B19,TODAY()-3,,0,0,1))))} -> 24.69 | H19: =E19*F19 -> 72750 | I19: =F19*G19 -> 123450 | J19: =I19-H19 -> 50700 | K19: =I19/H19-1 -> 0.69690722 | L19: =I19/$C$7 -> 0.13651971
B20: RENT3 | C20: 45383 | D20: BTG | E20: 55.12 | F20: 3000 | G20: {=IFERROR(_xlfn.STOCKHISTORY(B20,TODAY(),,0,0,1),IFERROR(_xlfn.STOCKHISTORY(B20,TODAY()-1,,0,0,1),IFERROR(_xlfn.STOCKHISTORY(B20,TODAY()-2,,0,0,1),_xlfn.STOCKHISTORY(B20,TODAY()-3,,0,0,1))))} -> 32.23 | H20: =E20*F20 -> 165360 | I20: =F20*G20 -> 96690 | J20: =I20-H20 -> -68670 | K20: =I20/H20-1 -> -0.41527576 | L20: =I20/$C$7 -> 0.10692662
B21: VISA34 | C21: 44228 | D21: BTG | E21: 14.55 | F21: 2500 | G21: {=IFERROR(_xlfn.STOCKHISTORY(B21,TODAY(),,0,0,1),IFERROR(_xlfn.STOCKHISTORY(B21,TODAY()-1,,0,0,1),IFERROR(_xlfn.STOCKHISTORY(B21,TODAY()-2,,0,0,1),_xlfn.STOCKHISTORY(B21,TODAY()-3,,0,0,1))))} -> 95.7 | H21: =E21*F21 -> 36375 | I21: =F21*G21 -> 239250 | J21: =I21-H21 -> 202875 | K21: =I21/H21-1 -> 5.5773196 | L21: =I21/$C$7 -> 0.26457952

Sheet Fundos
B5: Total Investido | C5: =SUM(G10:G87) -> 635568 | D5: ="Δ "&TEXT(C6-C5,"#.#") -> Δ -49.150 | E5: =C6/C5-1 -> -0.077332402
B6: Total Atual | C6: =SUM(H10:H87) -> 586418
B9: Ativo | C9: Data | D9: Preço Médio | E9: Quantidade | F9: Preço Atual | G9: Investido | H9: Atual | I9: L/P | J9: % L/P | K9: % Carteira FII
B10: XPML11 | C10: 44958 | D10: 100 | E10: 1000 | F10: {=IFERROR(_xlfn.STOCKHISTORY(B10,TODAY(),,0,0,1),IFERROR(_xlfn.STOCKHISTORY(B10,TODAY()-1,,0,0,1),IFERROR(_xlfn.STOCKHISTORY(B10,TODAY()-2,,0,0,1),_xlfn.STOCKHISTORY(B10,TODAY()-3,,0,0,1))))} -> 97.65 | G10: =D10*E10 -> 100000 | H10: =E10*F10 -> 97650 | I10: =H10-G10 -> -2350 | J10: =H10/G10-1 -> -0.0235 | K10: =H10/$C$6 -> 0.16651945
B11: HGLG11 | C11: 45108 | D11: 172.61 | E11: 300 | F11: {=IFERROR(_xlfn.STOCKHISTORY(B11,TODAY(),,0,0,1),IFERROR(_xlfn.STOCKHISTORY(B11,TODAY()-1,,0,0,1),IFERROR(_xlfn.STOCKHISTORY(B11,TODAY()-2,,0,0,1),_xlfn.STOCKHISTORY(B11,TODAY()-3,,0,0,1))))} -> 151.36 | G11: =D11*E11 -> 51783 | H11: =E11*F11 -> 45408 | I11: =H11-G11 -> -6375 | J11: =H11/G11-1 -> -0.1231099 | K11: =H11/$C$6 -> 0.077432821
B12: HGRE11 | C12: 45108 | D12: 115.01 | E12: 2000 | F12: {=IFERROR(_xlfn.STOCKHISTORY(B12,TODAY(),,0,0,1),IFERROR(_xlfn.STOCKHISTORY(B12,TODAY()-1,,0,0,1),IFERROR(_xlfn.STOCKHISTORY(B12,TODAY()-2,,0,0,1),_xlfn.STOCKHISTORY(B12,TODAY()-3,,0,0,1))))} -> 98.69 | G12: =D12*E12 -> 230020 | H12: =E12*F12 -> 197380 | I12: =H12-G12 -> -32640 | J12: =H12/G12-1 -> -0.1419007 | K12: =H12/$C$6 -> 0.33658585
B13: KNRI11 | C13: 45294 | D13: 117.2 | E13: 1000 | F13: {=IFERROR(_xlfn.STOCKHISTORY(B13,TODAY(),,0,0,1),IFERROR(_xlfn.STOCKHISTORY(B13,TODAY()-1,,0,0,1),IFERROR(_xlfn.STOCKHISTORY(B13,TODAY()-2,,0,0,1),_xlfn.STOCKHISTORY(B13,TODAY()-3,,0,0,1))))} -> 131.98 | G13: =D13*E13 -> 117200 | H13: =E13*F13 -> 131980 | I13: =H13-G13 -> 14780 | J13: =H13/G13-1 -> 0.12610922 | K13: =H13/$C$6 -> 0.2250613
B14: MXRF11 | C14: 45174 | D14: 9.5 | E14: 1500 | F14: {=IFERROR(_xlfn.STOCKHISTORY(B14,TODAY(),,0,0,1),IFERROR(_xlfn.STOCKHISTORY(B14,TODAY()-1,,0,0,1),IFERROR(_xlfn.STOCKHISTORY(B14,TODAY()-2,,0,0,1),_xlfn.STOCKHISTORY(B14,TODAY()-3,,0,0,1))))} -> 9.08 | G14: =D14*E14 -> 14250 | H14: =E14*F14 -> 13620 | I14: =H14-G14 -> -630 | J14: =H14/G14-1 -> -0.044210526 | K14: =H14/$C$6 -> 0.023225754
B15: VISC11 | C15: 44598 | D15: 120.5 | E15: 600 | F15: {=IFERROR(_xlfn.STOCKHISTORY(B15,TODAY(),,0,0,1),IFERROR(_xlfn.STOCKHISTORY(B15,TODAY()-1,,0,0,1),IFERROR(_xlfn.STOCKHISTORY(B15,TODAY()-2,,0,0,1),_xlfn.STOCKHISTORY(B15,TODAY()-3,,0,0,1))))} -> 92 | G15: =D15*E15 -> 72300 | H15: =E15*F15 -> 55200 | I15: =H15-G15 -> -17100 | J15: =H15/G15-1 -> -0.23651452 | K15: =H15/$C$6 -> 0.094130808
B16: XPLG11 | C16: 44866 | D16: 100.03 | E16: 500 | F16: {=IFERROR(_xlfn.STOCKHISTORY(B16,TODAY(),,0,0,1),IFERROR(_xlfn.STOCKHISTORY(B16,TODAY()-1,,0,0,1),IFERROR(_xlfn.STOCKHISTORY(B16,TODAY()-2,,0,0,1),_xlfn.STOCKHISTORY(B16,TODAY()-3,,0,0,1))))} -> 90.36 | G16: =D16*E16 -> 50015 | H16: =E16*F16 -> 45180 | I16: =H16-G16 -> -4835 | J16: =H16/G16-1 -> -0.096670999 | K16: =H16/$C$6 -> 0.07704402

Sheet Cripto
B7: Total Investido | C7: =SUM(G12:G100) -> 183344.55 | D7: ="Δ "&TEXT(C8-C7,"#.#") -> Δ 201.503 | E7: =C8/C7-1 -> 1.0990416
B8: Total Atual | C8: =SUM(H12:H100) -> 384847.84
B11: Tipo | C11: Data | D11: Preço Médio | E11: Quantidade | F11: Preço Atual | G11: Investido | H11: Atual | I11: L/P | J11: % L/P | K11: % Carteira Cripto
B12: BTC/USD | C12: 43922 | D12: 51693.5 | E12: 2.5 | F12: {=IFERROR(_xlfn.STOCKHISTORY(B12,TODAY(),,0,0,1),IFERROR(_xlfn.STOCKHISTORY(B12,TODAY()-1,,0,0,1),IFERROR(_xlfn.STOCKHISTORY(B12,TODAY()-2,,0,0,1),_xlfn.STOCKHISTORY(B12,TODAY()-3,,0,0,1))))} -> 101345 | G12: =D12*E12 -> 129233.75 | H12: =E12*F12 -> 253362.5 | I12: =H12-G12 -> 124128.75 | J12: =H12/G12-1 -> 0.96049793 | K12: =H12/$C$8 -> 0.65834461
B13: ETH/USD | C13: 44287 | D13: 1200.6 | E13: 18 | F13: {=IFERROR(_xlfn.STOCKHISTORY(B13,TODAY(),,0,0,1),IFERROR(_xlfn.STOCKHISTORY(B13,TODAY()-1,,0,0,1),IFERROR(_xlfn.STOCKHISTORY(B13,TODAY()-2,,0,0,1),_xlfn.STOCKHISTORY(B13,TODAY()-3,,0,0,1))))} -> 3903.63 | G13: =D13*E13 -> 21610.8 | H13: =E13*F13 -> 70265.34 | I13: =H13-G13 -> 48654.54 | J13: =H13/G13-1 -> 2.2513993 | K13: =H13/$C$8 -> 0.18257954
B14: LTC/USD | C14: 45017 | D14: 65 | E14: 500 | F14: {=IFERROR(_xlfn.STOCKHISTORY(B14,TODAY(),,0,0,1),IFERROR(_xlfn.STOCKHISTORY(B14,TODAY()-1,,0,0,1),IFERROR(_xlfn.STOCKHISTORY(B14,TODAY()-2,,0,0,1),_xlfn.STOCKHISTORY(B14,TODAY()-3,,0,0,1))))} -> 122.44 | G14: =D14*E14 -> 32500 | H14: =E14*F14 -> 61220 | I14: =H14-G14 -> 28720 | J14: =H14/G14-1 -> 0.88369231 | K14: =H14/$C$8 -> 0.15907586

Sheet Diversos
B6: Total Investido | C6: =SUM(H11:H100) -> 115000 | D6: ="Δ "&TEXT(C7-C6,"#.#") -> Δ -3.800 | E6: =C7/C6-1 -> -0.033043478
B7: Total Atual | C7: =SUM(I11:I100) -> 111200
B10: Data | C10: Tipo | D10: Nome | F10: Emissor | G10: Corretora | H10: Investido | I10: Atual | J10: L/P | K10: % L/P
B11: 45566 | C11: LCA | D11: XPTO | F11: XP | G11: XP | H11: 50000 | I11: 55600 | J11: =I11-H11 -> 5600 | K11: =I11/H11-1 -> 0.112
B12: 44713 | C12: LCI | D12: XPTO | F12: XP | G12: XP | H12: 65000 | I12: 55600 | J12: =I12-H12 -> -9400 | K12: =I12/H12-1 -> -0.14461538
